odoo/addons/l10n_it_fiscalcode_sale/README.rst
odoo/addons/l10n_it_fiscalcode_sale/__init__.py
odoo/addons/l10n_it_fiscalcode_sale/__manifest__.py
odoo/addons/l10n_it_fiscalcode_sale/i18n/it.po
odoo/addons/l10n_it_fiscalcode_sale/i18n/l10n_it_fiscalcode_sale.pot
odoo/addons/l10n_it_fiscalcode_sale/readme/CONTRIBUTORS.md
odoo/addons/l10n_it_fiscalcode_sale/readme/DESCRIPTION.md
odoo/addons/l10n_it_fiscalcode_sale/static/description/icon.png
odoo/addons/l10n_it_fiscalcode_sale/static/description/index.html
odoo/addons/l10n_it_fiscalcode_sale/views/sale_order_report.xml
odoo_addon_l10n_it_fiscalcode_sale-18.0.1.0.0.2.dist-info/METADATA
odoo_addon_l10n_it_fiscalcode_sale-18.0.1.0.0.2.dist-info/WHEEL
odoo_addon_l10n_it_fiscalcode_sale-18.0.1.0.0.2.dist-info/top_level.txt
odoo_addon_l10n_it_fiscalcode_sale-18.0.1.0.0.2.dist-info/RECORD
